PartSeg_smfish/__init__.py
PartSeg_smfish/_version.py
PartSeg_smfish/copy_labels.py
PartSeg_smfish/measurement.py
PartSeg_smfish/napari.yaml
PartSeg_smfish/segmentation.py
PartSeg_smfish/verify_points.py
PartSeg_smfish/_tests/__init__.py
PartSeg_smfish/_tests/test_copy_labels.py
PartSeg_smfish/_tests/test_segmentation.py
PartSeg_smfish-0.1.3.dist-info/LICENSE
PartSeg_smfish-0.1.3.dist-info/METADATA
PartSeg_smfish-0.1.3.dist-info/WHEEL
PartSeg_smfish-0.1.3.dist-info/entry_points.txt
PartSeg_smfish-0.1.3.dist-info/top_level.txt
PartSeg_smfish-0.1.3.dist-info/RECORD
