Metadata-Version: 2.1
Name: PartSeg-smfish
Version: 0.1.3
Summary: PartSeg and napari plugin for smfish data
Home-page: https://github.com/4DNucleome/PartSeg-smfish
Author: Grzegorz Bokota
Author-email: g.bokota@cent.uw.edu.pl
License: BSD-3-Clause
Project-URL: Bug Tracker, https://github.com/4DNucleome/PartSeg-smfish/issues
Project-URL: Documentation, https://github.com/4DNucleome/PartSeg-smfish#README.md
Project-URL: Source Code, https://github.com/4DNucleome/PartSeg-smfish
Project-URL: User Support, https://github.com/4DNucleome/PartSeg-smfish/issues
Classifier: Development Status :: 2 - Pre-Alpha
Classifier: Framework :: napari
Classifier: Intended Audience :: Developers
Classifier: License :: OSI Approved :: BSD License
Classifier: Operating System :: OS Independent
Classifier: Programming Language :: Python
Classifier: Programming Language :: Python :: 3
Classifier: Programming Language :: Python :: 3 :: Only
Classifier: Programming Language :: Python :: 3.8
Classifier: Programming Language :: Python :: 3.9
Classifier: Programming Language :: Python :: 3.10
Classifier: Topic :: Scientific/Engineering :: Image Processing
Requires-Python: >=3.8
License-File: LICENSE
Requires-Dist: PartSeg (>=0.13.0)
Requires-Dist: numpy
Requires-Dist: napari
Requires-Dist: qtpy
Provides-Extra: testing
Requires-Dist: tox ; extra == 'testing'
Requires-Dist: pytest ; extra == 'testing'
Requires-Dist: pytest-cov ; extra == 'testing'
Requires-Dist: pytest-qt ; extra == 'testing'
